docoseco/__init__.py
docoseco-1.0.0.dist-info/entry_points.txt
docoseco-1.0.0.dist-info/WHEEL
docoseco-1.0.0.dist-info/METADATA
docoseco-1.0.0.dist-info/RECORD
