Metadata-Version: 2.1
Name: docoseco
Version: 1.0.0
Summary: Automatize management of docker confgs and secrets 
Home-page: https://github.com/Zebradil/docoseco
License: MIT
Author: German Lashevich
Author-email: german.lashevich@gmail.com
Requires-Python: >=3.8,<4.0
Classifier: License :: OSI Approved :: MIT License
Classifier: Programming Language :: Python :: 3
Classifier: Programming Language :: Python :: 3.8
Requires-Dist: ruamel.yaml (>=0.16.10,<0.17.0)
Project-URL: Repository, https://github.com/Zebradil/docoseco
